[
    {
        "title": " ",
        "link": "https://product.29cm.co.kr/catalog/2767820?category_large_code=272100100",
        "image": "https://img.29cm.co.kr/item/202503/11eff8c7e38acf188b63a9b7d5e299ff.jpg?width=400&format=webp"
    },
    {
        "title": " ",
        "link": "https://product.29cm.co.kr/catalog/3110900?category_large_code=272100100",
        "image": "https://img.29cm.co.kr/item/202503/11effb19541dae2baceac1546d655d34.jpg?width=400&format=webp"
    },
    {
        "title": " ",
        "link": "https://product.29cm.co.kr/catalog/3060421?category_large_code=272100100",
        "image": "https://img.29cm.co.kr/item/202502/11efeab36fc239dd85211d78c7eccbfb.jpg?width=400&format=webp"
    },
    {
        "title": " ",
        "link": "https://product.29cm.co.kr/catalog/3126265?category_large_code=272100100",
        "image": "https://img.29cm.co.kr/item/202503/11f00001e93a13b28b63b14c0317855a.jpg?width=400&format=webp"
    },
    {
        "title": " ",
        "link": "https://product.29cm.co.kr/catalog/3098234?category_large_code=272100100",
        "image": "https://img.29cm.co.kr/item/202503/11eff984b6c83d15acea05b5a9680542.jpg?width=400&format=webp"
    },
    {
        "title": " ",
        "link": "https://product.29cm.co.kr/catalog/2764524?category_large_code=272100100",
        "image": "https://img.29cm.co.kr/item/202408/11ef65d5e5a79842a9804fcec6e7d148.jpg?width=400&format=webp"
    },
    {
        "title": " ",
        "link": "https://product.29cm.co.kr/catalog/1542206?category_large_code=272100100",
        "image": "https://img.29cm.co.kr/next-product/2022/05/04/4dc18fd1f33b40e5b0c3a9d9bb2e7462_20220504142608.jpg?width=400&format=webp"
    },
    {
        "title": " ",
        "link": "https://product.29cm.co.kr/catalog/2775601?category_large_code=272100100",
        "image": "https://img.29cm.co.kr/next-product/2025/02/10/4d7ac959456b4891853a4e4b05be7ede_20250210131618.jpg?width=400&format=webp"
    },
    {
        "title": " ",
        "link": "https://product.29cm.co.kr/catalog/3128679?category_large_code=272100100",
        "image": "https://img.29cm.co.kr/item/202503/11effe34f681c947aceab7ec27062263.jpg?width=400&format=webp"
    },
    {
        "title": " ",
        "link": "https://product.29cm.co.kr/catalog/2512193?category_large_code=272100100",
        "image": "https://img.29cm.co.kr/item/202403/11eeda9cbebf37ce91a5cd402625dba2.jpg?width=400&format=webp"
    },
    {
        "title": " ",
        "link": "https://product.29cm.co.kr/catalog/3081489?category_large_code=272100100",
        "image": "https://img.29cm.co.kr/item/202502/11efed05811fd0ce8f0aed3a1bd26d2a.jpg?width=400&format=webp"
    },
    {
        "title": " ",
        "link": "https://product.29cm.co.kr/catalog/1782202?category_large_code=272100100",
        "image": "https://img.29cm.co.kr/item/202410/11ef86d2e976b6508fb29f52ee4bbf96.jpg?width=400&format=webp"
    },
    {
        "title": " ",
        "link": "https://product.29cm.co.kr/catalog/3060428?category_large_code=272100100",
        "image": "https://img.29cm.co.kr/item/202502/11efeab34c23b9ce8f0ae3d0d70e885f.jpg?width=400&format=webp"
    },
    {
        "title": " ",
        "link": "https://product.29cm.co.kr/catalog/2032580?category_large_code=272100100",
        "image": "https://img.29cm.co.kr/item/202502/11efee8dcbb96908867e39ec9a1a4ae4.jpg?width=400&format=webp"
    },
    {
        "title": " ",
        "link": "https://product.29cm.co.kr/catalog/2845563?category_large_code=272100100",
        "image": "https://img.29cm.co.kr/item/202410/11ef8623a807911785199729e765c4f9.png?width=400&format=webp"
    },
    {
        "title": " ",
        "link": "https://product.29cm.co.kr/catalog/2759784?category_large_code=268100100",
        "image": "https://img.29cm.co.kr/item/202502/11efed8f864e28318521e355a5560caf.jpg?width=400&format=webp"
    },
    {
        "title": " ",
        "link": "https://product.29cm.co.kr/catalog/2975647?category_large_code=268100100",
        "image": "https://img.29cm.co.kr/item/202502/11efe778a16160f08f0a5b7ca1ac26f7.jpg?width=400&format=webp"
    },
    {
        "title": " ",
        "link": "https://product.29cm.co.kr/catalog/2809409?category_large_code=268100100",
        "image": "https://img.29cm.co.kr/item/202410/11ef81fe1eb09587b8a2e949fe63ac8d.jpg?width=400&format=webp"
    },
    {
        "title": " ",
        "link": "https://product.29cm.co.kr/catalog/2754703?category_large_code=268100100",
        "image": "https://img.29cm.co.kr/item/202503/11effa5ef3a2fe748b63e1e7d3193e70.jpg?width=400&format=webp"
    },
    {
        "title": " ",
        "link": "https://product.29cm.co.kr/catalog/2796061?category_large_code=268100100",
        "image": "https://img.29cm.co.kr/item/202409/11ef68d2a601a0de856ac9143a6e44eb.jpg?width=400&format=webp"
    },
    {
        "title": " ",
        "link": "https://product.29cm.co.kr/catalog/2975700?category_large_code=268100100",
        "image": "https://img.29cm.co.kr/item/202502/11efe77529e1fa228f0ab3dd142f5e65.jpg?width=400&format=webp"
    },
    {
        "title": " ",
        "link": "https://product.29cm.co.kr/catalog/3085403?category_large_code=268100100",
        "image": "https://img.29cm.co.kr/item/202503/11effa79e9f838568b63f9c9925176cb.jpg?width=400&format=webp"
    },
    {
        "title": " ",
        "link": "https://product.29cm.co.kr/catalog/2304256?category_large_code=268100100",
        "image": "https://img.29cm.co.kr/item/202502/11eff4b23a45223bacea2111496b488c.jpg?width=400&format=webp"
    },
    {
        "title": " ",
        "link": "https://product.29cm.co.kr/catalog/3076810?category_large_code=268100100",
        "image": "https://img.29cm.co.kr/item/202503/11f0009e2e42fc4baceab5de028ac31d.jpg?width=400&format=webp"
    },
    {
        "title": " ",
        "link": "https://product.29cm.co.kr/catalog/2895688?category_large_code=268100100",
        "image": "https://img.29cm.co.kr/item/202410/11ef8c2cf04f675b85197d7700de27b1.jpg?width=400&format=webp"
    },
    {
        "title": " ",
        "link": "https://product.29cm.co.kr/catalog/3091691?category_large_code=268100100",
        "image": "https://img.29cm.co.kr/item/202503/11eff9922a67ecabacea4996c71d2532.jpg?width=400&format=webp"
    },
    {
        "title": " ",
        "link": "https://product.29cm.co.kr/catalog/3113500?category_large_code=268100100",
        "image": "https://img.29cm.co.kr/item/202503/11eff97ced4a60388b637f6533aa7516.jpg?width=400&format=webp"
    },
    {
        "title": " ",
        "link": "https://product.29cm.co.kr/catalog/2207379?category_large_code=268100100",
        "image": "https://img.29cm.co.kr/item/202502/11efe8350123ab1a8f0a699d75c06ccd.jpg?width=400&format=webp"
    },
    {
        "title": " ",
        "link": "https://product.29cm.co.kr/catalog/2451991?category_large_code=268100100",
        "image": "https://img.29cm.co.kr/item/202501/11efd9f30ef6cb8585210772433225cd.jpg?width=400&format=webp"
    },
    {
        "title": " ",
        "link": "https://product.29cm.co.kr/catalog/774410?category_large_code=268100100",
        "image": "https://img.29cm.co.kr/item/202402/11eed4654d4903148377557fd6184c5d.jpg?width=400&format=webp"
    },
    {
        "title": " ",
        "link": "https://product.29cm.co.kr/catalog/2850695?category_large_code=268100100",
        "image": "https://img.29cm.co.kr/item/202503/11effd164b3f44a68b6389f5a13bde58.jpg?width=400&format=webp"
    },
    {
        "title": " ",
        "link": "https://product.29cm.co.kr/catalog/2203405?category_large_code=268100100",
        "image": "https://img.29cm.co.kr/item/202503/11f0007a3d6c8ec48b63132e4278d6f3.jpg?width=400&format=webp"
    },
    {
        "title": " ",
        "link": "https://product.29cm.co.kr/catalog/1841835?category_large_code=268100100",
        "image": "https://img.29cm.co.kr/item/202408/11ef5add963a26018362cfd85935fc61.jpeg?width=400&format=webp"
    },
    {
        "title": " ",
        "link": "https://product.29cm.co.kr/catalog/2763258?category_large_code=268100100",
        "image": "https://img.29cm.co.kr/item/202408/11ef5ad6f2de71518362b36d371886b5.jpeg?width=400&format=webp"
    },
    {
        "title": " ",
        "link": "https://product.29cm.co.kr/catalog/2195644?category_large_code=268100100",
        "image": "https://img.29cm.co.kr/item/202308/11ee461613c3d5aeacc5bf24744a93e9.jpg?width=400&format=webp"
    },
    {
        "title": " ",
        "link": "https://product.29cm.co.kr/catalog/1260646?categoryLargeCode=290100100&categoryMediumCode=&sort=RECOMMEND&defaultSort=RECOMMEND&sortOrder=DESC&page=1",
        "image": "https://img.29cm.co.kr/next-product/2023/10/11/36233895c45c446b8feaed1b3e47a0bf_20231011131741.jpg?width=400&format=webp"
    },
    {
        "title": " ",
        "link": "https://product.29cm.co.kr/catalog/3027882?categoryLargeCode=290100100&categoryMediumCode=&sort=RECOMMEND&defaultSort=RECOMMEND&sortOrder=DESC&page=1",
        "image": "https://img.29cm.co.kr/item/202501/11efd2eb864f8332ad1b3742833e2771.jpg?width=400&format=webp"
    },
    {
        "title": " ",
        "link": "https://product.29cm.co.kr/catalog/3091223?categoryLargeCode=290100100&categoryMediumCode=&sort=RECOMMEND&defaultSort=RECOMMEND&sortOrder=DESC&page=1",
        "image": "https://img.29cm.co.kr/item/202502/11efef1ebeb624fd8f140135192e2857.jpg?width=400&format=webp"
    },
    {
        "title": " ",
        "link": "https://product.29cm.co.kr/catalog/1848669?categoryLargeCode=290100100&categoryMediumCode=&sort=RECOMMEND&defaultSort=RECOMMEND&sortOrder=DESC&page=1",
        "image": "https://img.29cm.co.kr/next-product/2023/06/02/7aae2529b4f444f98f7f8976dd66544a_20230602135538.jpg?width=400&format=webp"
    },
    {
        "title": " ",
        "link": "https://product.29cm.co.kr/catalog/2718740?categoryLargeCode=290100100&categoryMediumCode=&sort=RECOMMEND&defaultSort=RECOMMEND&sortOrder=DESC&page=1",
        "image": "https://img.29cm.co.kr/item/202411/11efaae8c6ba57b39d18cd7435c9ff6b.jpg?width=400&format=webp"
    },
    {
        "title": " ",
        "link": "https://product.29cm.co.kr/catalog/3007111?categoryLargeCode=290100100&categoryMediumCode=&sort=RECOMMEND&defaultSort=RECOMMEND&sortOrder=DESC&page=1",
        "image": "https://img.29cm.co.kr/next-product/2024/12/31/bdc7209dd3704d92a7f07a89c584a9aa_20241231160918.jpg?width=400&format=webp"
    },
    {
        "title": " ",
        "link": "https://product.29cm.co.kr/catalog/2612077?categoryLargeCode=290100100&categoryMediumCode=&sort=RECOMMEND&defaultSort=RECOMMEND&sortOrder=DESC&page=1",
        "image": "https://img.29cm.co.kr/item/202411/11efab0df080016d93168764272ca9d6.jpg?width=400&format=webp"
    },
    {
        "title": " ",
        "link": "https://product.29cm.co.kr/catalog/2844180?categoryLargeCode=290100100&categoryMediumCode=&sort=RECOMMEND&defaultSort=RECOMMEND&sortOrder=DESC&page=1",
        "image": "https://img.29cm.co.kr/item/202409/11ef7c7438e978679714e7d614a6948c.jpg?width=400&format=webp"
    },
    {
        "title": " ",
        "link": "https://product.29cm.co.kr/catalog/3091302?categoryLargeCode=290100100&categoryMediumCode=&sort=RECOMMEND&defaultSort=RECOMMEND&sortOrder=DESC&page=1",
        "image": "https://img.29cm.co.kr/item/202502/11efef2316fdf2fd8f140d56920ab0f2.jpg?width=400&format=webp"
    },
    {
        "title": " ",
        "link": "https://product.29cm.co.kr/catalog/1746192?categoryLargeCode=290100100&categoryMediumCode=&sort=RECOMMEND&defaultSort=RECOMMEND&sortOrder=DESC&page=1",
        "image": "https://img.29cm.co.kr/item/202412/11efc359d90df16aad1be1b9504d0dd0.png?width=400&format=webp"
    },
    {
        "title": " ",
        "link": "https://product.29cm.co.kr/catalog/3091316?categoryLargeCode=290100100&categoryMediumCode=&sort=RECOMMEND&defaultSort=RECOMMEND&sortOrder=DESC&page=1",
        "image": "https://img.29cm.co.kr/item/202502/11eff2685dca8a3faceaddafca5fefc0.jpg?width=400&format=webp"
    },
    {
        "title": " ",
        "link": "https://product.29cm.co.kr/catalog/2433361?categoryLargeCode=290100100&categoryMediumCode=&sort=RECOMMEND&defaultSort=RECOMMEND&sortOrder=DESC&page=1",
        "image": "https://img.29cm.co.kr/item/202405/11ef1384905c8d05b9bb27f0bc266bbe.jpg?width=400&format=webp"
    },
    {
        "title": " ",
        "link": "https://product.29cm.co.kr/catalog/2536248?categoryLargeCode=290100100&categoryMediumCode=&sort=RECOMMEND&defaultSort=RECOMMEND&sortOrder=DESC&page=1",
        "image": "https://img.29cm.co.kr/item/202403/11eee2a2e10abafe82f2dd7ebb407111.jpg?width=400&format=webp"
    },
    {
        "title": " ",
        "link": "https://product.29cm.co.kr/catalog/3091666?categoryLargeCode=290100100&categoryMediumCode=&sort=RECOMMEND&defaultSort=RECOMMEND&sortOrder=DESC&page=1",
        "image": "https://img.29cm.co.kr/item/202502/11eff275625ea6108b63070e0727d9c4.jpg?width=400&format=webp"
    },
    {
        "title": " ",
        "link": "https://product.29cm.co.kr/catalog/2363261?categoryLargeCode=290100100&categoryMediumCode=&sort=RECOMMEND&defaultSort=RECOMMEND&sortOrder=DESC&page=1",
        "image": "https://img.29cm.co.kr/item/202312/11ee93de4ffe1b41a5b39b5f05c7c4b3.jpg?width=400&format=webp"
    },
    {
        "title": " ",
        "link": "https://product.29cm.co.kr/catalog/3011215?categoryLargeCode=290100100&categoryMediumCode=&sort=RECOMMEND&defaultSort=RECOMMEND&sortOrder=DESC&page=1",
        "image": "https://img.29cm.co.kr/item/202501/11efcaa43b805ce38521cfd097ccf8ee.jpg?width=400&format=webp"
    },
    {
        "title": " ",
        "link": "https://product.29cm.co.kr/catalog/2326404?categoryLargeCode=290100100&categoryMediumCode=&sort=RECOMMEND&defaultSort=RECOMMEND&sortOrder=DESC&page=1",
        "image": "https://img.29cm.co.kr/next-product/2023/11/07/1a5037cb5b6642bdaa9f3ca2a4585940_20231107165652.jpg?width=400&format=webp"
    },
    {
        "title": " ",
        "link": "https://product.29cm.co.kr/catalog/2309024?categoryLargeCode=290100100&categoryMediumCode=&sort=RECOMMEND&defaultSort=RECOMMEND&sortOrder=DESC&page=1",
        "image": "https://img.29cm.co.kr/item/202310/11ee73cb97c17f53a5b32dd0ac28ae0c.JPG?width=400&format=webp"
    },
    {
        "title": " ",
        "link": "https://product.29cm.co.kr/catalog/2892276?categoryLargeCode=290100100&categoryMediumCode=&sort=RECOMMEND&defaultSort=RECOMMEND&sortOrder=DESC&page=1",
        "image": "https://img.29cm.co.kr/item/202410/11ef8ac1a2a2bd318519816d3de8b838.jpg?width=400&format=webp"
    },
    {
        "title": " ",
        "link": "https://product.29cm.co.kr/catalog/2269982?categoryLargeCode=290100100&categoryMediumCode=&sort=RECOMMEND&defaultSort=RECOMMEND&sortOrder=DESC&page=1",
        "image": "https://img.29cm.co.kr/next-product/2023/10/04/44dd180c3592410997dd8f79be295ef8_20231004134334.jpg?width=400&format=webp"
    }
]