[
    {
        "title": "4월 14일 오늘의 증시현황(퓨리오사AI 관련주↑)",
        "link": "https://kakao777.tistory.com/8133",
        "image": "https://raw.githubusercontent.com/ric-grown/news-bot/main/images/blog_tistory_63.jpg"
    },
    {
        "title": "부드럽고 담백한 아보카도 버거, 집에서도 간편하게",
        "link": "https://msdm.tistory.com/entry/%EB%B6%80%EB%93%9C%EB%9F%BD%EA%B3%A0-%EB%8B%B4%EB%B0%B1%ED%95%9C-%EC%95%84%EB%B3%B4%EC%B9%B4%EB%8F%84-%EB%B2%84%EA%B1%B0-%EC%A7%91%EC%97%90%EC%84%9C%EB%8F%84-%EA%B0%84%ED%8E%B8%ED%95%98%EA%B2%8C",
        "image": "https://raw.githubusercontent.com/ric-grown/news-bot/main/images/blog_tistory_42.jpg"
    },
    {
        "title": " ",
        "link": "https://product.29cm.co.kr/catalog/3007465?categoryLargeCode=290100100&categoryMediumCode=&sort=RECOMMEND&defaultSort=RECOMMEND&sortOrder=DESC&page=1",
        "image": "https://img.29cm.co.kr/item/202501/11efc838b71bf0c185217f793c6c2671.jpg?width=400&format=webp"
    },
    {
        "title": "사복 패션도 이쁜 카리나 프라다 가방 원피스 코디",
        "link": "https://blog.naver.com/romyday/223834350432",
        "image": "https://raw.githubusercontent.com/ric-grown/news-bot/main/images/blog_tistory_25.jpg"
    },
    {
        "title": " ",
        "link": "https://product.29cm.co.kr/catalog/3168142?category_large_code=272100100",
        "image": "https://img.29cm.co.kr/item/202503/11f008ab14ecd3478e7bb1051fe6ba3c.jpg?width=400&format=webp"
    },
    {
        "title": "친구 이정후는 미국서 홈런 뻥뻥 치는데…9년째 기다린다! ML 꿈꾸던 1m97 거인, 여전히 뜨거운 기다림 [SC피플]",
        "link": "https://m.sports.naver.com/article/076/0004266268",
        "image": "https://raw.githubusercontent.com/ric-grown/news-bot/main/images/sports_2.jpg"
    },
    {
        "title": "경북 경산 아파트서 불···주민 4명 연기 흡입",
        "link": "https://n.news.naver.com/article/657/0000037275?ntype=RANKING",
        "image": "https://imgnews.pstatic.net/image/657/2025/04/16/0000037275_002_20250416075815282.jpeg?type=w860"
    },
    {
        "title": "Cat's claw trumpet",
        "link": "https://4mahpk.tistory.com/entry/Cats-claw-trumpet",
        "image": "https://raw.githubusercontent.com/ric-grown/news-bot/main/images/blog_tistory_45.jpg"
    },
    {
        "title": "갤럭시 OneUI 7 업데이트 중단이유 향후 일정은?",
        "link": "https://blog.naver.com/dicagallery/223833670966",
        "image": "https://raw.githubusercontent.com/ric-grown/news-bot/main/images/blog_tistory_8.jpg"
    },
    {
        "title": "이만한 밥도둑 없습니다! 삼겹살 김치찜",
        "link": "https://01195077236.tistory.com/3146",
        "image": "https://raw.githubusercontent.com/ric-grown/news-bot/main/images/blog_tistory_38.jpg"
    },
    {
        "title": "'충격' 토트넘 '오피셜' 발표…\"손흥민 발 부상\" 유로파리그 100% 컨디션 '만드는 중→선수 관리 차원'",
        "link": "https://m.sports.naver.com/article/477/0000545071",
        "image": "https://raw.githubusercontent.com/ric-grown/news-bot/main/images/sports_21.jpg"
    },
    {
        "title": " ",
        "link": "https://product.29cm.co.kr/catalog/2971856?categoryLargeCode=290100100&categoryMediumCode=&sort=RECOMMEND&defaultSort=RECOMMEND&sortOrder=DESC&page=1",
        "image": "https://img.29cm.co.kr/item/202411/11efae14076dcd76ad1bef0ff3e10215.jpg?width=400&format=webp"
    },
    {
        "title": "함께 어린이날 보내고 나무 심고… 거리 좁히는 대한항공·아시아나",
        "link": "https://n.news.naver.com/article/366/0001069602?ntype=RANKING",
        "image": "https://imgnews.pstatic.net/image/366/2025/04/16/0001069602_001_20250416074108688.JPG?type=w860"
    },
    {
        "title": "북유럽 신화 2 - 신들의 전쟁 : 에시르·바니르 전쟁 및 라그나로크, 피블윈터",
        "link": "https://bong3614.tistory.com/463",
        "image": "https://raw.githubusercontent.com/ric-grown/news-bot/main/images/blog_tistory_71.jpg"
    },
    {
        "title": "안젤리나졸리•마리아칼라스! 영화 ‘마리아‘",
        "link": "https://jyshine24.tistory.com/1048",
        "image": "https://raw.githubusercontent.com/ric-grown/news-bot/main/images/blog_tistory_77.jpg"
    },
    {
        "title": "일본은 이미 축제! '日 손흥민' 미토마(28세, 리버풀) 대형 이적 터진다...亞 역대 최고 이적료 경신 예고→\"이적료 1500억이면 합의\"",
        "link": "https://m.sports.naver.com/article/076/0004266708",
        "image": "https://raw.githubusercontent.com/ric-grown/news-bot/main/images/sports_33.jpg"
    },
    {
        "title": "'타율 .103→.389' 방출 걱정 끝, 플로리얼 살아났는데…왜 문현빈은 중견수 준비하나",
        "link": "https://m.sports.naver.com/article/109/0005283605",
        "image": "https://raw.githubusercontent.com/ric-grown/news-bot/main/images/sports_14.jpg"
    },
    {
        "title": "김정민, 길거리 흡연 딱 걸렸다…나이 논란에 소속사 \"처우 검토중\"",
        "link": "https://v.daum.net/v/20250416064223447",
        "image": "https://img1.daumcdn.net/thumb/S130x90ht.u/?fname=https%3A%2F%2Ft1.daumcdn.net%2Fnews%2F202504%2F16%2FSpoChosun%2F20250416064224086ywzs.jpg&scode=media"
    },
    {
        "title": "이디야 데못죽 콜라보 매장 배달 세트 한정판 굿즈 정보",
        "link": "https://blog.naver.com/hyjueng/223833772895",
        "image": "https://raw.githubusercontent.com/ric-grown/news-bot/main/images/blog_tistory_18.jpg"
    },
    {
        "title": "슈만 피아노 5중주 피아노 퀸텟 Op. 44 1 2 3 4 악장 Eb장조 내림 마장조 Schumann Piano Quintet Op. 44 Eb Major",
        "link": "https://blog.naver.com/wjdghk7695/223833612690",
        "image": "https://raw.githubusercontent.com/ric-grown/news-bot/main/images/blog_tistory_24.jpg"
    },
    {
        "title": "독특한 1인극 화이트래빗 레드래빗 소개",
        "link": "https://blog.naver.com/silver6312/223833874790",
        "image": "https://raw.githubusercontent.com/ric-grown/news-bot/main/images/blog_tistory_11.jpg"
    },
    {
        "title": "다큐 어른 김장하 그리고 문형배 이야기",
        "link": "https://interestingtopicofconversation.tistory.com/entry/%EB%8B%A4%ED%81%90-%EC%96%B4%EB%A5%B8-%EA%B9%80%EC%9E%A5%ED%95%98-%EA%B7%B8%EB%A6%AC%EA%B3%A0-%EB%AC%B8%ED%98%95%EB%B0%B0-%EC%9D%B4%EC%95%BC%EA%B8%B0",
        "image": "https://raw.githubusercontent.com/ric-grown/news-bot/main/images/blog_tistory_67.jpg"
    },
    {
        "title": "유시민 <그의 운명에 대한 아주 개인적인 생각>, 어떤 희망이 우리에게",
        "link": "https://breezehu.tistory.com/998",
        "image": "https://raw.githubusercontent.com/ric-grown/news-bot/main/images/blog_tistory_66.jpg"
    },
    {
        "title": "“답답하다”며 활주로서 비상문 연 승객…에어서울 이륙 포기",
        "link": "https://n.news.naver.com/article/021/0002703148?ntype=RANKING",
        "image": "https://imgnews.pstatic.net/image/021/2025/04/15/0002703148_002_20250415112310299.jpg?type=w860"
    },
    {
        "title": "<대가족> 추천 영화 리뷰",
        "link": "https://lalagongjoo.tistory.com/538",
        "image": "https://raw.githubusercontent.com/ric-grown/news-bot/main/images/blog_tistory_72.jpg"
    },
    {
        "title": " ",
        "link": "https://product.29cm.co.kr/catalog/3082533?category_large_code=268100100",
        "image": "https://img.29cm.co.kr/item/202502/11efed1526e78d488f0a0facaaef9a28.jpg?width=400&format=webp"
    },
    {
        "title": "포토샵 2025 지브리 감성 벚꽃 보정",
        "link": "https://stock0901.tistory.com/entry/%ED%8F%AC%ED%86%A0%EC%83%B5-2025-%EC%A7%80%EB%B8%8C%EB%A6%AC-%EA%B0%90%EC%84%B1-%EB%B2%9A%EA%BD%83-%EB%B3%B4%EC%A0%95",
        "image": "https://raw.githubusercontent.com/ric-grown/news-bot/main/images/blog_tistory_57.jpg"
    },
    {
        "title": "2025 대덕문화전당 기획 전시 / MAESTRO 3",
        "link": "https://cho-a47.tistory.com/3192",
        "image": "https://raw.githubusercontent.com/ric-grown/news-bot/main/images/blog_tistory_75.jpg"
    },
    {
        "title": " ",
        "link": "https://product.29cm.co.kr/catalog/3093478?category_large_code=268100100",
        "image": "https://img.29cm.co.kr/item/202503/11effb1b3788b71facea4ba4749b1097.jpg?width=400&format=webp"
    },
    {
        "title": "하정우가 추천한 '빨리 걷기' 해보니…놀라운 효과 나타났다 [건강!톡]",
        "link": "https://n.news.naver.com/article/015/0005119770?ntype=RANKING",
        "image": "https://imgnews.pstatic.net/image/015/2025/04/16/0005119770_001_20250416074016438.jpg?type=w860"
    },
    {
        "title": "“뿌리기만 해도 ‘풍성’” 나오자마자 품절 대란…‘마법 샴푸’ 이어 ‘탈모 스프레이’ 나왔다",
        "link": "https://n.news.naver.com/article/016/0002457707?ntype=RANKING",
        "image": "https://imgnews.pstatic.net/image/016/2025/04/15/0002457707_001_20250415184011140.jpg?type=w860"
    },
    {
        "title": "이건주, 44년 만에 생모 재회·눈물의 포옹…母 재혼 근황에 '충격' (아빠하고)",
        "link": "https://v.daum.net/v/20250416085006074",
        "image": "https://img1.daumcdn.net/thumb/S130x90ht.u/?fname=https%3A%2F%2Ft1.daumcdn.net%2Fnews%2F202504%2F16%2Fxportsnews%2F20250416085007606gavg.jpg&scode=media"
    },
    {
        "title": "[미국 주식 시황] 4월 9일 경제 뉴스와 시장 반응 : 트럼프 풋! 관세 유예 발표",
        "link": "https://kkm3503.tistory.com/entry/%EB%AF%B8%EA%B5%AD-%EC%A3%BC%EC%8B%9D-%EC%8B%9C%ED%99%A9-4%EC%9B%94-9%EC%9D%BC-%EA%B2%BD%EC%A0%9C-%EB%89%B4%EC%8A%A4%EC%99%80-%EC%8B%9C%EC%9E%A5-%EB%B0%98%EC%9D%91-%ED%8A%B8%EB%9F%BC%ED%94%84-%ED%92%8B-%EA%B4%80%EC%84%B8-%EC%9C%A0%EC%98%88-%EB%B0%9C%ED%91%9C",
        "image": "https://raw.githubusercontent.com/ric-grown/news-bot/main/images/blog_tistory_64.jpg"
    },
    {
        "title": " ",
        "link": "https://product.29cm.co.kr/catalog/2156573?category_large_code=272100100",
        "image": "https://img.29cm.co.kr/item/202308/11ee3021e5e073bea5ca8fa572bf858f.jpg?width=400&format=webp"
    },
    {
        "title": "슬전생 2화, 오이영 구도원 겹사돈? PD 작가 신원호 이우정 아니네",
        "link": "https://blog.naver.com/above_cloud/223833506036",
        "image": "https://raw.githubusercontent.com/ric-grown/news-bot/main/images/blog_tistory_16.jpg"
    },
    {
        "title": " ",
        "link": "https://product.29cm.co.kr/catalog/2430342?category_large_code=272100100",
        "image": "https://img.29cm.co.kr/item/202402/11eec3e23f4d9c3c8377c5593ffdaafa.jpg?width=400&format=webp"
    },
    {
        "title": "엔화 올라도 \"이정도면\"...일본 더 갔다",
        "link": "https://n.news.naver.com/article/215/0001205933?ntype=RANKING",
        "image": "https://imgnews.pstatic.net/image/215/2025/04/16/A202504160227_1_20250416063107703.jpg?type=w860"
    },
    {
        "title": "“잠금 해제가 안돼요” 업뎃 후 먹통에 ‘분노 폭발’…발칵 뒤집힌 ‘삼성’ 결국",
        "link": "https://n.news.naver.com/article/016/0002457765?ntype=RANKING",
        "image": "https://imgnews.pstatic.net/image/016/2025/04/15/0002457765_001_20250415223908340.png?type=w860"
    },
    {
        "title": "가성비 ipTIME 유무선 와이파이 공유기 써보니",
        "link": "https://sosmikuru.tistory.com/5651",
        "image": "https://raw.githubusercontent.com/ric-grown/news-bot/main/images/blog_tistory_53.jpg"
    },
    {
        "title": "紫桃(자도) 꽃이 피었다",
        "link": "https://bmkmotor3.tistory.com/entry/%E7%B4%AB%E6%A1%83%EC%9E%90%EB%8F%84-%EA%BD%83%EC%9D%B4-%ED%94%BC%EC%97%88%EB%8B%A4",
        "image": "https://raw.githubusercontent.com/ric-grown/news-bot/main/images/blog_tistory_49.jpg"
    },
    {
        "title": " ",
        "link": "https://product.29cm.co.kr/catalog/2829224?category_large_code=272100100",
        "image": "https://img.29cm.co.kr/item/202409/11ef703efcfc6f74856a8d19cd445baa.jpg?width=400&format=webp"
    },
    {
        "title": "\"비행기 1등석 안부럽다!\" 럭셔리 끝판왕이라는 벤츠 마이바흐 S680, 실물 직접 살펴보니",
        "link": "https://motoroid.tistory.com/5469",
        "image": "https://raw.githubusercontent.com/ric-grown/news-bot/main/images/blog_tistory_79.jpg"
    },
    {
        "title": "“한국형 챗GPT 전국민 무료 사용” 이재명 AI 주요 공약 분석해보니",
        "link": "https://n.news.naver.com/article/023/0003899775?ntype=RANKING",
        "image": "https://imgnews.pstatic.net/image/023/2025/04/16/0003899775_001_20250416082809924.jpg?type=w860"
    },
    {
        "title": " ",
        "link": "https://product.29cm.co.kr/catalog/2739920?category_large_code=268100100",
        "image": "https://img.29cm.co.kr/item/202408/11ef52fc40f79c2d83628f2b87a426cf.jpg?width=400&format=webp"
    },
    {
        "title": " ",
        "link": "https://product.29cm.co.kr/catalog/555363?categoryLargeCode=290100100&categoryMediumCode=&sort=RECOMMEND&defaultSort=RECOMMEND&sortOrder=DESC&page=1",
        "image": "https://img.29cm.co.kr/next-product/2022/09/19/166c169077754c74be9e10d2800347eb_20220919123547.jpg?width=400&format=webp"
    },
    {
        "title": "'이재용 세일즈 통했다'…삼성전기, BYD에 MLCC 공급",
        "link": "https://n.news.naver.com/article/215/0001205928?ntype=RANKING",
        "image": "https://imgnews.pstatic.net/image/215/2025/04/15/A202504150602_1_20250416061307539.jpg?type=w860"
    },
    {
        "title": " ",
        "link": "https://product.29cm.co.kr/catalog/931646?categoryLargeCode=290100100&categoryMediumCode=&sort=RECOMMEND&defaultSort=RECOMMEND&sortOrder=DESC&page=1",
        "image": "https://img.29cm.co.kr/next-product/2020/12/18/2baf37633f75441fb632ed500ed6ad1b_20201218003332.jpg?width=400&format=webp"
    },
    {
        "title": "'더 브라위너 패스→손흥민 마무리' 역대급 조합 뜬다! 英 매체 \"토트넘, 상위권 복귀 위해 상황 주시해야\"",
        "link": "https://m.sports.naver.com/article/117/0003932700",
        "image": "https://raw.githubusercontent.com/ric-grown/news-bot/main/images/sports_1.jpg"
    },
    {
        "title": " ",
        "link": "https://product.29cm.co.kr/catalog/2461030?category_large_code=268100100",
        "image": "https://img.29cm.co.kr/next-product/2024/02/13/4851e15c68df4442b11df7ae32375379_20240213181642.jpg?width=400&format=webp"
    },
    {
        "title": "SF 라인업 떴다! ‘연타석 홈런→KKK’ 이정후 3번 CF 출격…ERA 1점대 좌완 넘어설까",
        "link": "https://m.sports.naver.com/article/109/0005284440",
        "image": "https://raw.githubusercontent.com/ric-grown/news-bot/main/images/sports_37.jpg"
    }
]